aapayout/__init__.py
aapayout/admin.py
aapayout/app_settings.py
aapayout/apps.py
aapayout/auth_hooks.py
aapayout/constants.py
aapayout/context_processors.py
aapayout/forms.py
aapayout/helpers.py
aapayout/models.py
aapayout/tasks.py
aapayout/urls.py
aapayout/views.py
aapayout/locale/.gitkeep
aapayout/migrations/0001_initial.py
aapayout/migrations/0002_fleetparticipant_excluded_from_payout_and_more.py
aapayout/migrations/0003_esi_fleet_import.py
aapayout/migrations/0004_remove_fleet_doctrine_remove_fleet_location_and_more.py
aapayout/migrations/0005_fleet_finalized_fleet_finalized_at_and_more.py
aapayout/migrations/0006_lootpool_scout_shares.py
aapayout/migrations/0007_remove_lootpool_scout_bonus_percentage.py
aapayout/migrations/__init__.py
aapayout/services/__init__.py
aapayout/services/esi_fleet.py
aapayout/services/esi_wallet.py
aapayout/services/janice.py
aapayout/static/aapayout/.gitkeep
aapayout/static/aapayout/css/aapayout.css
aapayout/static/aapayout/js/aapayout.js
aapayout/templates/aapayout/base.html
aapayout/templates/aapayout/dashboard.html
aapayout/templates/aapayout/express_mode.html
aapayout/templates/aapayout/fleet_create.html
aapayout/templates/aapayout/fleet_detail.html
aapayout/templates/aapayout/fleet_edit.html
aapayout/templates/aapayout/fleet_import_results.html
aapayout/templates/aapayout/fleet_list.html
aapayout/templates/aapayout/loot_approve.html
aapayout/templates/aapayout/loot_detail.html
aapayout/templates/aapayout/loot_edit.html
aapayout/templates/aapayout/participant_edit.html
aapayout/templates/aapayout/payout_history.html
aapayout/templates/aapayout/payout_list.html
aapayout/templates/aapayout/payout_mark_paid.html
aapayout/templates/aapayout/verification_results.html
aapayout/templates/aapayout/verify_payments.html
aapayout/templatetags/__init__.py
aapayout/templatetags/aapayout_filters.py
aapayout/tests/__init__.py
aapayout/tests/test_deduplication.py
aapayout/tests/test_esi_fleet_import.py
aapayout/tests/test_example.py
aa_payout-0.3.18.dist-info/METADATA
aa_payout-0.3.18.dist-info/WHEEL
aa_payout-0.3.18.dist-info/licenses/LICENSE
aa_payout-0.3.18.dist-info/RECORD
