Metadata-Version: 2.4
Name: aa-payout
Version: 0.3.18
Summary: Fleet loot valuation and payout system for Alliance Auth
Project-URL: Changelog, https://github.com/guarzo/aa-payout/blob/master/CHANGELOG.md
Project-URL: Issue / Bug Reports, https://github.com/guarzo/aa-payout/issues
Author-email: Guarzo <guarzo.eve@gmail.com>
License: MIT License
License-File: LICENSE
Keywords: allianceauth,eveonline,fleet,payout
Classifier: Environment :: Web Environment
Classifier: Framework :: Django
Classifier: Framework :: Django :: 4.2
Classifier: Intended Audience :: End Users/Desktop
Classifier: License :: OSI Approved :: MIT License
Classifier: Operating System :: OS Independent
Classifier: Programming Language :: Python
Classifier: Programming Language :: Python :: 3 :: Only
Classifier: Programming Language :: Python :: 3.10
Classifier: Programming Language :: Python :: 3.11
Classifier: Programming Language :: Python :: 3.12
Classifier: Programming Language :: Python :: 3.13
Classifier: Topic :: Internet :: WWW/HTTP
Classifier: Topic :: Internet :: WWW/HTTP :: Dynamic Content
Requires-Python: >=3.10
Requires-Dist: allianceauth<5,>=4.3.1
Requires-Dist: django-esi>=5.0.0
Requires-Dist: django-eveuniverse>=1.6.0
Requires-Dist: requests>=2.28.0
